MANIFEST.in
README_PUBLIC.md
setup.cfg
setup.py
humanity_etl/__init__.py
humanity_etl/__main__.py
humanity_etl/humanity_etl.py
humanity_etl.egg-info/PKG-INFO
humanity_etl.egg-info/SOURCES.txt
humanity_etl.egg-info/dependency_links.txt
humanity_etl.egg-info/requires.txt
humanity_etl.egg-info/top_level.txt
humanity_etl/libs/__init__.py
humanity_etl/libs/cnst.py
humanity_etl/libs/dbg.py
humanity_etl/libs/network.py
humanity_etl/libs/transform.py
humanity_etl/tables/__init__.py
humanity_etl/tables/timeclocks.py
tests/__init__.py