Metadata-Version: 2.1
Name: humanity-etl
Version: 0.1.0
Summary: Replicate humanity data in databricks
Home-page: https://github.com/neofinancial/humanity_etl
Author: Neo Financial
Author-email: engineering@neofinancial.com
License: UNLICENSED
Platform: UNKNOWN
Classifier: Development Status :: 2 - Pre-Alpha
Classifier: Intended Audience :: Developers
Classifier: Natural Language :: English
Classifier: Programming Language :: Python :: 3
Requires-Python: >=3.6
